cognee_sdk/__init__.py
cognee_sdk/client.py
cognee_sdk/exceptions.py
cognee_sdk/models.py
cognee_sdk/py.typed
cognee_sdk-0.3.0.dist-info/licenses/LICENSE
cognee_sdk-0.3.0.dist-info/METADATA
cognee_sdk-0.3.0.dist-info/WHEEL
cognee_sdk-0.3.0.dist-info/top_level.txt
cognee_sdk-0.3.0.dist-info/RECORD
