Metadata-Version: 2.4
Name: cognee-sdk
Version: 0.3.0
Summary: Lightweight Python SDK for Cognee - AI Memory Platform
Author: CozyCognee Team
License-Expression: MIT
Project-URL: Homepage, https://github.com/your-org/cognee-sdk
Project-URL: Documentation, https://github.com/your-org/cognee-sdk#readme
Project-URL: Repository, https://github.com/your-org/cognee-sdk
Project-URL: Issues, https://github.com/your-org/cognee-sdk/issues
Keywords: cognee,ai,memory,knowledge-graph,rag,sdk
Classifier: Development Status :: 3 - Alpha
Classifier: Intended Audience :: Developers
Classifier: Programming Language :: Python :: 3
Classifier: Programming Language :: Python :: 3.10
Classifier: Programming Language :: Python :: 3.11
Classifier: Programming Language :: Python :: 3.12
Classifier: Topic :: Software Development :: Libraries :: Python Modules
Classifier: Topic :: Scientific/Engineering :: Artificial Intelligence
Requires-Python: >=3.10
License-File: LICENSE
Requires-Dist: httpx>=0.25.0
Requires-Dist: pydantic>=2.0.0
Requires-Dist: typing-extensions>=4.0.0
Provides-Extra: http2
Requires-Dist: httpx[http2]>=0.25.0; extra == "http2"
Provides-Extra: websocket
Requires-Dist: websockets>=12.0; extra == "websocket"
Provides-Extra: dev
Requires-Dist: pytest>=7.0.0; extra == "dev"
Requires-Dist: pytest-asyncio>=0.21.0; extra == "dev"
Requires-Dist: pytest-cov>=4.0.0; extra == "dev"
Requires-Dist: black>=23.0.0; extra == "dev"
Requires-Dist: ruff>=0.1.0; extra == "dev"
Requires-Dist: mypy>=1.0.0; extra == "dev"
Requires-Dist: types-requests; extra == "dev"
Dynamic: license-file
